{"object_name": "AFSK 300 AX.25 +0Hz", "object_type": "demod_chain", "modem": {"type": "afsk",  "config": "300", "options": {"correlator_offset": "0.0"}}, "slicer": {"type": "binary", "config": "300", "options": {"lock_rate": "0.90"}}, "stream": {"type": "lfsr", "options": {"poly": "0x3", "invert": "True"}}, "codec": {"type": "ax25"}}
{"object_name": "AFSK 300 AX.25 +5Hz", "object_type": "demod_chain", "modem": {"type": "afsk",  "config": "300", "options": {"correlator_offset": "5.0"}}, "slicer": {"type": "binary", "config": "300", "options": {"lock_rate": "0.90"}}, "stream": {"type": "lfsr", "options": {"poly": "0x3", "invert": "True"}}, "codec": {"type": "ax25"}}
{"object_name": "AFSK 300 AX.25 -5Hz", "object_type": "demod_chain", "modem": {"type": "afsk",  "config": "300", "options": {"correlator_offset": "-5.0"}}, "slicer": {"type": "binary", "config": "300", "options": {"lock_rate": "0.90"}}, "stream": {"type": "lfsr", "options": {"poly": "0x3", "invert": "True"}}, "codec": {"type": "ax25"}}
{"object_name": "Decoded header report", "object_type": "report", "options": {"style": "decoded_headers", "destination": "std_out"}}